[
    {
        "threadID": "8584325014958475",
        "url": "https://files.catbox.moe/sh24ne.jpeg",
        "report": {}
    },
    {
        "threadID": "8524968764231306",
        "url": "https://files.catbox.moe/ygz549.jpeg",
        "report": {}
    },
    {
        "threadID": "27714580081523286",
        "url": "https://files.catbox.moe/lwo9t4.jpeg",
        "report": {}
    },
    {
        "threadID": "28430160453249170",
        "url": "https://files.catbox.moe/veknb8.jpeg",
        "report": {}
    }
]