{
    "total": [
        {
            "id": "61554886974766",
            "count": 0
        },
        {
            "id": "100033827252261",
            "count": 42
        },
        {
            "id": "61557293481880",
            "count": 44
        },
        {
            "id": "100077038275962",
            "count": 0
        },
        {
            "id": "61565655363507",
            "count": 40
        },
        {
            "id": "100079136541437",
            "count": 0
        },
        {
            "id": "100095457253523",
            "count": 42
        },
        {
            "id": "100077573461968",
            "count": 0
        },
        {
            "id": "61558677281155",
            "count": 0
        },
        {
            "id": "100051525424541",
            "count": 1
        },
        {
            "id": "100085457852057",
            "count": 0
        },
        {
            "id": "100082335708743",
            "count": 0
        },
        {
            "id": "61555632365104",
            "count": 0
        },
        {
            "id": "100095474042779",
            "count": 0
        },
        {
            "id": "61561270005948",
            "count": 0
        },
        {
            "id": "100072840644112",
            "count": 8
        },
        {
            "id": "61570561451023",
            "count": 0
        },
        {
            "id": "100078516261928",
            "count": 0
        },
        {
            "id": "100081753576472",
            "count": 0
        },
        {
            "id": "100082555426237",
            "count": 0
        },
        {
            "id": "100092513839449",
            "count": 0
        },
        {
            "id": "100078267596853",
            "count": 0
        },
        {
            "id": "61556982819781",
            "count": 5
        },
        {
            "id": "100034985235308",
            "count": 27
        },
        {
            "id": "61554019574449",
            "count": 0
        },
        {
            "id": "100077366272669",
            "count": 1
        },
        {
            "id": "61556306213282",
            "count": 1
        },
        {
            "id": "61569532929991",
            "count": 1
        },
        {
            "id": "61559345886514",
            "count": 0
        },
        {
            "id": "100076206406549",
            "count": 75
        },
        {
            "id": "61569751031983",
            "count": 0
        },
        {
            "id": "100034763851145",
            "count": 0
        },
        {
            "id": "100027459618308",
            "count": 0
        },
        {
            "id": "61561161715392",
            "count": 6
        },
        {
            "id": "61565454512501",
            "count": 0
        },
        {
            "id": "61568704994619",
            "count": 5
        },
        {
            "id": "100036293868033",
            "count": 0
        },
        {
            "id": "61565448015927",
            "count": 0
        },
        {
            "id": "61561929966427",
            "count": 0
        }
    ],
    "week": [
        {
            "id": "61554886974766",
            "count": 0
        },
        {
            "id": "100033827252261",
            "count": 42
        },
        {
            "id": "61557293481880",
            "count": 44
        },
        {
            "id": "100077038275962",
            "count": 0
        },
        {
            "id": "61565655363507",
            "count": 40
        },
        {
            "id": "100079136541437",
            "count": 0
        },
        {
            "id": "100095457253523",
            "count": 42
        },
        {
            "id": "100077573461968",
            "count": 0
        },
        {
            "id": "61558677281155",
            "count": 0
        },
        {
            "id": "100051525424541",
            "count": 1
        },
        {
            "id": "100085457852057",
            "count": 0
        },
        {
            "id": "100082335708743",
            "count": 0
        },
        {
            "id": "61555632365104",
            "count": 0
        },
        {
            "id": "100095474042779",
            "count": 0
        },
        {
            "id": "61561270005948",
            "count": 0
        },
        {
            "id": "100072840644112",
            "count": 8
        },
        {
            "id": "61570561451023",
            "count": 0
        },
        {
            "id": "100078516261928",
            "count": 0
        },
        {
            "id": "100081753576472",
            "count": 0
        },
        {
            "id": "100082555426237",
            "count": 0
        },
        {
            "id": "100092513839449",
            "count": 0
        },
        {
            "id": "100078267596853",
            "count": 0
        },
        {
            "id": "61556982819781",
            "count": 5
        },
        {
            "id": "100034985235308",
            "count": 27
        },
        {
            "id": "61554019574449",
            "count": 0
        },
        {
            "id": "100077366272669",
            "count": 1
        },
        {
            "id": "61556306213282",
            "count": 1
        },
        {
            "id": "61569532929991",
            "count": 1
        },
        {
            "id": "61559345886514",
            "count": 0
        },
        {
            "id": "100076206406549",
            "count": 75
        },
        {
            "id": "61569751031983",
            "count": 0
        },
        {
            "id": "100034763851145",
            "count": 0
        },
        {
            "id": "100027459618308",
            "count": 0
        },
        {
            "id": "61561161715392",
            "count": 6
        },
        {
            "id": "61565454512501",
            "count": 0
        },
        {
            "id": "61568704994619",
            "count": 5
        },
        {
            "id": "100036293868033",
            "count": 0
        },
        {
            "id": "61565448015927",
            "count": 0
        },
        {
            "id": "61561929966427",
            "count": 0
        }
    ],
    "day": [
        {
            "id": "61554886974766",
            "count": 0,
            "name": "Do Thuy Dung"
        },
        {
            "id": "100033827252261",
            "count": 17,
            "name": "Ngân Trịnh"
        },
        {
            "id": "61557293481880",
            "count": 33,
            "name": "Bichh Duyenn"
        },
        {
            "id": "100077038275962",
            "count": 0,
            "name": "Học Mẫn"
        },
        {
            "id": "61565655363507",
            "count": 4,
            "name": "Tear Stains"
        },
        {
            "id": "100079136541437",
            "count": 0,
            "name": "Kim Ngân"
        },
        {
            "id": "100095457253523",
            "count": 0,
            "name": "Mihh Chau"
        },
        {
            "id": "100077573461968",
            "count": 0,
            "name": "Phạm Minh Anh"
        },
        {
            "id": "61558677281155",
            "count": 0,
            "name": "Hà Vy"
        },
        {
            "id": "100051525424541",
            "count": 1,
            "name": "Avis De'Morte"
        },
        {
            "id": "100085457852057",
            "count": 0,
            "name": "Nguyễn Thị"
        },
        {
            "id": "100082335708743",
            "count": 0,
            "name": "Hai Anh"
        },
        {
            "id": "61555632365104",
            "count": 0,
            "name": "Ngọcc Thư"
        },
        {
            "id": "100095474042779",
            "count": 0,
            "name": "Người dùng Facebook"
        },
        {
            "id": "61561270005948",
            "count": 0,
            "name": "Thanh Trúc"
        },
        {
            "id": "100072840644112",
            "count": 6,
            "name": "Trúc Nguyễn Vy"
        },
        {
            "id": "61570561451023",
            "count": 0,
            "name": "Trương Thảo My"
        },
        {
            "id": "100078516261928",
            "count": 0,
            "name": "Người dùng Facebook"
        },
        {
            "id": "100081753576472",
            "count": 0,
            "name": "Dii Emm"
        },
        {
            "id": "100082555426237",
            "count": 0,
            "name": "Nthb Ngoc"
        },
        {
            "id": "100092513839449",
            "count": 0,
            "name": "Người dùng Facebook"
        },
        {
            "id": "100078267596853",
            "count": 0,
            "name": "Qh Chi"
        },
        {
            "id": "61556982819781",
            "count": 5,
            "name": "Phạm Nhi"
        },
        {
            "id": "100034985235308",
            "count": 5,
            "name": "Đka Khang"
        },
        {
            "id": "61554019574449",
            "count": 0,
            "name": "Bảo Khánh"
        },
        {
            "id": "100077366272669",
            "count": 0,
            "name": "Phạm Thanh Tùng"
        },
        {
            "id": "61556306213282",
            "count": 0,
            "name": "Chau Anh Nguyen"
        },
        {
            "id": "61569532929991",
            "count": 1,
            "name": "Kim Eui Hyun"
        },
        {
            "id": "61559345886514",
            "count": 0,
            "name": "Bùi Thảo Chi"
        },
        {
            "id": "100076206406549",
            "count": 26,
            "name": "Đình Vũ"
        },
        {
            "id": "61569751031983",
            "count": 0,
            "name": "Thảo Nghi"
        },
        {
            "id": "100034763851145",
            "count": 0,
            "name": "Trà Đào Cam Sả"
        },
        {
            "id": "100027459618308",
            "count": 0,
            "name": "Nhut Le"
        },
        {
            "id": "61561161715392",
            "count": 3,
            "name": "Hoang Anh Dương"
        },
        {
            "id": "61565454512501",
            "count": 0,
            "name": "Người dùng Facebook"
        },
        {
            "id": "61568704994619",
            "count": 1,
            "name": "Tú Lưu"
        },
        {
            "id": "100036293868033",
            "count": 0,
            "name": "Ngoc Yen"
        },
        {
            "id": "61565448015927",
            "count": 0,
            "name": "Mi Mii"
        },
        {
            "id": "61561929966427",
            "count": 0,
            "name": "Thanh Thanh"
        }
    ],
    "time": 0,
    "last": {
        "time": 6,
        "day": [
            {
                "id": "61554886974766",
                "count": 0,
                "name": "Do Thuy Dung"
            },
            {
                "id": "100033827252261",
                "count": 25,
                "name": "Ngân Trịnh"
            },
            {
                "id": "61557293481880",
                "count": 11,
                "name": "Bichh Duyenn"
            },
            {
                "id": "100077038275962",
                "count": 0,
                "name": "Học Mẫn"
            },
            {
                "id": "61565655363507",
                "count": 36,
                "name": "Tear Stains"
            },
            {
                "id": "100079136541437",
                "count": 0,
                "name": "Kim Ngân"
            },
            {
                "id": "100095457253523",
                "count": 42,
                "name": "Mihh Chau"
            },
            {
                "id": "100077573461968",
                "count": 0,
                "name": "Phạm Minh Anh"
            },
            {
                "id": "61558677281155",
                "count": 0,
                "name": "Hà Vy"
            },
            {
                "id": "100051525424541",
                "count": 0,
                "name": "Avis De'Morte"
            },
            {
                "id": "100085457852057",
                "count": 0,
                "name": "Nguyễn Thị"
            },
            {
                "id": "100082335708743",
                "count": 0,
                "name": "Hai Anh"
            },
            {
                "id": "61555632365104",
                "count": 0,
                "name": "Ngọcc Thư"
            },
            {
                "id": "100095474042779",
                "count": 0,
                "name": "Người dùng Facebook"
            },
            {
                "id": "61561270005948",
                "count": 0,
                "name": "Thanh Trúc"
            },
            {
                "id": "100072840644112",
                "count": 2,
                "name": "Trúc Nguyễn Vy"
            },
            {
                "id": "61570561451023",
                "count": 0,
                "name": "Trương Thảo My"
            },
            {
                "id": "100078516261928",
                "count": 0,
                "name": "Người dùng Facebook"
            },
            {
                "id": "100081753576472",
                "count": 0,
                "name": "Dii Emm"
            },
            {
                "id": "100082555426237",
                "count": 0,
                "name": "Nthb Ngoc"
            },
            {
                "id": "100092513839449",
                "count": 0,
                "name": "Người dùng Facebook"
            },
            {
                "id": "100078267596853",
                "count": 0,
                "name": "Qh Chi"
            },
            {
                "id": "61556982819781",
                "count": 0,
                "name": "Phạm Nhi"
            },
            {
                "id": "100034985235308",
                "count": 22,
                "name": "Đka Khang"
            },
            {
                "id": "61554019574449",
                "count": 0,
                "name": "Bảo Khánh"
            },
            {
                "id": "100077366272669",
                "count": 1,
                "name": "Phạm Thanh Tùng"
            },
            {
                "id": "61556306213282",
                "count": 1,
                "name": "Chau Anh Nguyen"
            },
            {
                "id": "61569532929991",
                "count": 0,
                "name": "Kim Eui Hyun"
            },
            {
                "id": "61559345886514",
                "count": 0,
                "name": "Bùi Thảo Chi"
            },
            {
                "id": "100076206406549",
                "count": 49,
                "name": "Đình Vũ"
            },
            {
                "id": "61569751031983",
                "count": 0,
                "name": "Thảo Nghi"
            },
            {
                "id": "100034763851145",
                "count": 0,
                "name": "Trà Đào Cam Sả"
            },
            {
                "id": "100027459618308",
                "count": 0,
                "name": "Nhut Le"
            },
            {
                "id": "61561161715392",
                "count": 3,
                "name": "Hoang Anh Dương"
            },
            {
                "id": "61565454512501",
                "count": 0,
                "name": "Người dùng Facebook"
            },
            {
                "id": "61568704994619",
                "count": 4,
                "name": "Tú Lưu"
            },
            {
                "id": "100036293868033",
                "count": 0,
                "name": "Ngoc Yen"
            },
            {
                "id": "61565448015927",
                "count": 0,
                "name": "Mi Mii"
            },
            {
                "id": "61561929966427",
                "count": 0,
                "name": "Thanh Thanh"
            }
        ],
        "week": [
            {
                "id": "61554886974766",
                "count": 0
            },
            {
                "id": "100033827252261",
                "count": 0
            },
            {
                "id": "61557293481880",
                "count": 0
            },
            {
                "id": "100077038275962",
                "count": 0
            },
            {
                "id": "61565655363507",
                "count": 0
            },
            {
                "id": "100079136541437",
                "count": 0
            },
            {
                "id": "100095457253523",
                "count": 0
            },
            {
                "id": "100077573461968",
                "count": 0
            },
            {
                "id": "61558677281155",
                "count": 0
            },
            {
                "id": "100051525424541",
                "count": 0
            },
            {
                "id": "100085457852057",
                "count": 0
            },
            {
                "id": "100082335708743",
                "count": 0
            },
            {
                "id": "61555632365104",
                "count": 0
            },
            {
                "id": "100095474042779",
                "count": 0
            },
            {
                "id": "61561270005948",
                "count": 0
            },
            {
                "id": "100072840644112",
                "count": 0
            },
            {
                "id": "61551998037427",
                "count": 0
            },
            {
                "id": "61570561451023",
                "count": 0
            },
            {
                "id": "100078516261928",
                "count": 0
            },
            {
                "id": "100081753576472",
                "count": 0
            },
            {
                "id": "100082555426237",
                "count": 0
            },
            {
                "id": "100092513839449",
                "count": 0
            },
            {
                "id": "100078267596853",
                "count": 0
            },
            {
                "id": "61556982819781",
                "count": 0
            },
            {
                "id": "100034985235308",
                "count": 0
            },
            {
                "id": "61554019574449",
                "count": 0
            },
            {
                "id": "100077366272669",
                "count": 0
            },
            {
                "id": "61556306213282",
                "count": 0
            },
            {
                "id": "61569532929991",
                "count": 0
            },
            {
                "id": "61559345886514",
                "count": 0
            },
            {
                "id": "100076206406549",
                "count": 0
            },
            {
                "id": "61569751031983",
                "count": 0
            },
            {
                "id": "100034763851145",
                "count": 0
            },
            {
                "id": "100027459618308",
                "count": 0
            },
            {
                "id": "61561161715392",
                "count": 0
            },
            {
                "id": "61565454512501",
                "count": 0
            },
            {
                "id": "61568704994619",
                "count": 0
            },
            {
                "id": "100036293868033",
                "count": 0
            },
            {
                "id": "61565448015927",
                "count": 0
            },
            {
                "id": "61561929966427",
                "count": 0
            }
        ]
    }
}